aioherepy/__init__.py
aioherepy/aiohere_api.py
aioherepy/here_enum.py
aioherepy/here_error.py
aioherepy-0.1.0.dist-info/LICENSE
aioherepy-0.1.0.dist-info/WHEEL
aioherepy-0.1.0.dist-info/METADATA
aioherepy-0.1.0.dist-info/RECORD
